README.rst
setup.py
django_rickroll.egg-info/PKG-INFO
django_rickroll.egg-info/SOURCES.txt
django_rickroll.egg-info/dependency_links.txt
django_rickroll.egg-info/top_level.txt
rickroll/__init__.py
rickroll/exceptions.py
rickroll/middleware.py
rickroll/models.py