Metadata-Version: 1.0
Name: django-rickroll
Version: 0.1.1
Summary: Rickrolling Django middleware to annoy potential hackers
Home-page: https://github.com/codeinthehole/django-rickroll
Author: David Winterbottom
Author-email: david.winterbottom@gmail.com
License: Copyright (C) 2012 David Winterbottom
